syncedPB/__init__.py
syncedPB-0.0.3.dist-info/LICENSE
syncedPB-0.0.3.dist-info/METADATA
syncedPB-0.0.3.dist-info/WHEEL
syncedPB-0.0.3.dist-info/top_level.txt
syncedPB-0.0.3.dist-info/RECORD
